{
    "version-major": 267,
    "version-minor": 0,
    "mt-model-info": {
        "version": "MT-pivot-Dawn-v267-20231128-f1e2fb111",
        "language-pairs": [
            "id_ID-th_TH",
            "th_TH-id_ID"
        ],
        "tasks": [
            "mt_app",
            "mt_app_greedy",
            "system",
            "system_greedy"
        ]
    },
    "text-proc": {},
    "mt-decoders": {
        "mt_app": {
            "engine-type": "PDEC",
            "block-definitions": {
                "id_ID-th_TH-PhraseBookBlock": {
                    "block-type": "PhraseBookBlock",
                    "enable": true,
                    "nbest": 4,
                    "pb-file-list": "PB-id/PB/id-th.mt_app+mt_app_greedy+siri+system+system_greedy+web.dict",
                    "asset-name": "PB-id"
                },
                "id_ID-th_TH-SentencePieceBlockEncode": {
                    "block-type": "SentencePieceBlock",
                    "action": "encode",
                    "sentence-piece-file": "MT-bi-en-id-th-vi-20/MT/spm.model",
                    "asset-name": "MT-bi-en-id-th-vi-20"
                },
                "id_ID-th_TH-PDecTranslatorBlock": {
                    "block-type": "PDecTranslatorBlock",
                    "model-file": "MT-bi-en-id-th-vi-20/MT/pyespresso.mdl.bin",
                    "model-type": "espresso",
                    "engine-type": "PDEC",
                    "enable-memory-map": true,
                    "confidence-model-file": "",
                    "confidence-threshold": 0,
                    "use-sentencepiece-ids": true,
                    "beam": 3,
                    "lm-mode": "partial_bias",
                    "lm-weight": 0.25,
                    "max-seq-length": 200,
                    "max-seq-length-floor": 80,
                    "max-seq-length-relative": 2,
                    "norm-costs": true,
                    "partial-input-override": {
                        "beam": 1,
                        "lm-weight": 0.3,
                        "source-token": "partial> <src-id_ID",
                        "veto-factor": 0.0
                    },
                    "reset-meta-info": false,
                    "rs-beam": 0.66,
                    "source-locale": "id_ID",
                    "source-token": "id_ID",
                    "target-locale": "th_TH",
                    "target-token": "th_TH> <id_ID-th_TH-optimal",
                    "unk-replace": true,
                    "veto-factor": 0,
                    "enable_shortlist": true,
                    "merge_shortlist": true,
                    "shortlist-cond-n": 100,
                    "shortlist-freq-n": 100,
                    "shortlist-lang-pair": "all-th",
                    "asset-name": "MT-bi-en-id-th-vi-20"
                },
                "id_ID-th_TH-SelectBlock": {
                    "block-type": "SelectBlock",
                    "match-key": "alignment-queries",
                    "match-wildcard": "**",
                    "match-pattern": [
                        {
                            "start": "**",
                            "end": "**"
                        }
                    ]
                },
                "id_ID-th_TH-PDecForceAlignBlock": {
                    "block-type": "PDecForceAlignBlock",
                    "model-file": "MT-bi-en-id-th-vi-20/MT/pyespresso.mdl.bin",
                    "model-type": "espresso",
                    "nbest": 4,
                    "source-locale": "id_ID",
                    "target-locale": "th_TH",
                    "source-token": "id_ID",
                    "target-token": "th_TH> <id_ID-th_TH-optimal",
                    "use-sentencepiece-ids": true,
                    "enable_shortlist": true,
                    "merge_shortlist": true,
                    "shortlist-cond-n": 100,
                    "shortlist-freq-n": 100,
                    "shortlist-lang-pair": "all-th",
                    "asset-name": "MT-bi-en-id-th-vi-20"
                },
                "id_ID-th_TH-SentencePieceBlockDecode": {
                    "block-type": "SentencePieceBlock",
                    "action": "decode",
                    "sentence-piece-file": "MT-bi-en-id-th-vi-20/MT/spm.model",
                    "asset-name": "MT-bi-en-id-th-vi-20"
                },
                "id_ID-th_TH-AlignmentProcessorBlock": {
                    "block-type": "AlignmentProcessorBlock",
                    "avoid-crossing-words": false,
                    "word-level-alignments": false
                },
                "id_ID-th_TH-FilterBlock": {
                    "locale-validation": true,
                    "source-locale": "id_ID",
                    "block-type": "FilterBlock",
                    "nbest": 1,
                    "enable": true
                },
                "id_ID-th_TH-CaseMapBlock": {
                    "block-type": "CaseMapBlock",
                    "locale": "id"
                },
                "th_TH-id_ID-PhraseBookBlock": {
                    "block-type": "PhraseBookBlock",
                    "enable": true,
                    "nbest": 4,
                    "pb-file-list": "PB-th/PB/th-id.mt_app+mt_app_greedy+siri+system+system_greedy+web.dict",
                    "asset-name": "PB-th"
                },
                "th_TH-id_ID-SentencePieceBlockEncode": {
                    "block-type": "SentencePieceBlock",
                    "action": "encode",
                    "sentence-piece-file": "MT-bi-en-id-th-vi-20/MT/spm.model",
                    "asset-name": "MT-bi-en-id-th-vi-20"
                },
                "th_TH-id_ID-PDecTranslatorBlock": {
                    "block-type": "PDecTranslatorBlock",
                    "model-file": "MT-bi-en-id-th-vi-20/MT/pyespresso.mdl.bin",
                    "model-type": "espresso",
                    "engine-type": "PDEC",
                    "enable-memory-map": true,
                    "confidence-model-file": "",
                    "confidence-threshold": 0,
                    "use-sentencepiece-ids": true,
                    "beam": 3,
                    "lm-mode": "partial_bias",
                    "lm-weight": 0.25,
                    "max-seq-length": 200,
                    "max-seq-length-floor": 80,
                    "max-seq-length-relative": 2,
                    "norm-costs": true,
                    "partial-input-override": {
                        "beam": 1,
                        "lm-weight": 0.3,
                        "source-token": "partial> <src-th_TH",
                        "veto-factor": 0.0
                    },
                    "reset-meta-info": false,
                    "rs-beam": 0.66,
                    "source-locale": "th_TH",
                    "source-token": "th_TH",
                    "target-locale": "id_ID",
                    "target-token": "id_ID> <th_TH-id_ID-optimal",
                    "unk-replace": true,
                    "veto-factor": 0,
                    "enable_shortlist": true,
                    "merge_shortlist": true,
                    "shortlist-cond-n": 100,
                    "shortlist-freq-n": 100,
                    "shortlist-lang-pair": "all-id",
                    "asset-name": "MT-bi-en-id-th-vi-20"
                },
                "th_TH-id_ID-SelectBlock": {
                    "block-type": "SelectBlock",
                    "match-key": "alignment-queries",
                    "match-wildcard": "**",
                    "match-pattern": [
                        {
                            "start": "**",
                            "end": "**"
                        }
                    ]
                },
                "th_TH-id_ID-PDecForceAlignBlock": {
                    "block-type": "PDecForceAlignBlock",
                    "model-file": "MT-bi-en-id-th-vi-20/MT/pyespresso.mdl.bin",
                    "model-type": "espresso",
                    "nbest": 4,
                    "source-locale": "th_TH",
                    "target-locale": "id_ID",
                    "source-token": "th_TH",
                    "target-token": "id_ID> <th_TH-id_ID-optimal",
                    "use-sentencepiece-ids": true,
                    "enable_shortlist": true,
                    "merge_shortlist": true,
                    "shortlist-cond-n": 100,
                    "shortlist-freq-n": 100,
                    "shortlist-lang-pair": "all-id",
                    "asset-name": "MT-bi-en-id-th-vi-20"
                },
                "th_TH-id_ID-SentencePieceBlockDecode": {
                    "block-type": "SentencePieceBlock",
                    "action": "decode",
                    "sentence-piece-file": "MT-bi-en-id-th-vi-20/MT/spm.model",
                    "asset-name": "MT-bi-en-id-th-vi-20"
                },
                "th_TH-id_ID-AlignmentTokenizerBlock": {
                    "block-type": "SimpleTokenizerBlock",
                    "tokenizer-file": "MT-bi-en-id-th-vi-20/MT/tokenizer.pat",
                    "asset-name": "MT-bi-en-id-th-vi-20"
                },
                "th_TH-id_ID-AlignmentProcessorBlock": {
                    "block-type": "AlignmentProcessorBlock",
                    "avoid-crossing-words": true,
                    "word-level-alignments": false,
                    "tokenizer": "simple"
                },
                "th_TH-id_ID-FilterBlock": {
                    "locale-validation": true,
                    "source-locale": "th_TH",
                    "block-type": "FilterBlock",
                    "nbest": 1,
                    "enable": true
                },
                "th_TH-id_ID-CaseMapBlock": {
                    "block-type": "CaseMapBlock",
                    "locale": "th"
                }
            },
            "language-pair-specific-settings": {
                "id_ID-th_TH": {
                    "graph": {
                        "pb": {
                            "receive-from": "graph-input",
                            "block": "id_ID-th_TH-PhraseBookBlock"
                        },
                        "spm_encode": {
                            "receive-from": "pb",
                            "block": "id_ID-th_TH-SentencePieceBlockEncode"
                        },
                        "pdec": {
                            "receive-from": "spm_encode",
                            "block": "id_ID-th_TH-PDecTranslatorBlock"
                        },
                        "spm_encode_pb_translation": {
                            "receive-from": "pb:final",
                            "block": "id_ID-th_TH-SentencePieceBlockEncode"
                        },
                        "merge_encoded_translations": {
                            "receive-from": {
                                "in2": "pdec",
                                "in1": "spm_encode_pb_translation"
                            },
                            "block-type": "MergerBlock",
                            "merge-style": "any"
                        },
                        "select_source_spc": {
                            "receive-from": {
                                "control": "merge_encoded_translations",
                                "value": "graph-input"
                            },
                            "block-type": "SelectBlock",
                            "match-key": "status",
                            "match-pattern": "phrasebook_exact"
                        },
                        "null_1": {
                            "receive-from": "select_source_spc:pass",
                            "block-type": "NullBlock"
                        },
                        "spm_encode_src": {
                            "receive-from": "select_source_spc:match",
                            "block": "id_ID-th_TH-SentencePieceBlockEncode"
                        },
                        "select_source": {
                            "receive-from": {
                                "control": "spm_encode_src",
                                "value": "spm_encode_src"
                            },
                            "block": "id_ID-th_TH-SelectBlock"
                        },
                        "select_target": {
                            "receive-from": {
                                "value": "spm_encode_pb_translation",
                                "control": "spm_encode_src"
                            },
                            "block": "id_ID-th_TH-SelectBlock"
                        },
                        "merge_encoded_source": {
                            "receive-from": {
                                "in2": "spm_encode",
                                "in1": "spm_encode_src"
                            },
                            "block-type": "MergerBlock",
                            "merge-style": "any"
                        },
                        "null_2": {
                            "receive-from": "select_source:match",
                            "block-type": "NullBlock"
                        },
                        "force_align": {
                            "receive-from": {
                                "source": "select_source:pass",
                                "target": "select_target:pass"
                            },
                            "block": "id_ID-th_TH-PDecForceAlignBlock"
                        },
                        "merge_translations_with_needed_alignment_info": {
                            "receive-from": {
                                "in3": "pdec",
                                "in1": "select_target:match",
                                "in2": "force_align"
                            },
                            "block-type": "MergerBlock",
                            "merge-style": "any"
                        },
                        "spm_decode": {
                            "receive-from": "merge_translations_with_needed_alignment_info",
                            "block": "id_ID-th_TH-SentencePieceBlockDecode"
                        },
                        "alignment": {
                            "receive-from": {
                                "segmentor-encode": "merge_encoded_source",
                                "pdec-decode": "spm_decode:tokens",
                                "segmentor-decode": "spm_decode",
                                "source": "graph-input"
                            },
                            "block": "id_ID-th_TH-AlignmentProcessorBlock"
                        },
                        "filter": {
                            "receive-from": "alignment",
                            "block": "id_ID-th_TH-FilterBlock"
                        },
                        "casemap_final": {
                            "receive-from": "filter",
                            "block": "id_ID-th_TH-CaseMapBlock"
                        },
                        "do_not_translate": {
                            "receive-from": {
                                "target": "casemap_final",
                                "source": "graph-input"
                            },
                            "block-type": "DoNotTranslateBlock"
                        },
                        "graph-output": {
                            "receive-from": "do_not_translate"
                        }
                    }
                },
                "th_TH-id_ID": {
                    "graph": {
                        "pb": {
                            "receive-from": "graph-input",
                            "block": "th_TH-id_ID-PhraseBookBlock"
                        },
                        "spm_encode": {
                            "receive-from": "pb",
                            "block": "th_TH-id_ID-SentencePieceBlockEncode"
                        },
                        "pdec": {
                            "receive-from": "spm_encode",
                            "block": "th_TH-id_ID-PDecTranslatorBlock"
                        },
                        "spm_encode_pb_translation": {
                            "receive-from": "pb:final",
                            "block": "th_TH-id_ID-SentencePieceBlockEncode"
                        },
                        "merge_encoded_translations": {
                            "receive-from": {
                                "in2": "pdec",
                                "in1": "spm_encode_pb_translation"
                            },
                            "block-type": "MergerBlock",
                            "merge-style": "any"
                        },
                        "select_source_spc": {
                            "receive-from": {
                                "control": "merge_encoded_translations",
                                "value": "graph-input"
                            },
                            "block-type": "SelectBlock",
                            "match-key": "status",
                            "match-pattern": "phrasebook_exact"
                        },
                        "null_1": {
                            "receive-from": "select_source_spc:pass",
                            "block-type": "NullBlock"
                        },
                        "spm_encode_src": {
                            "receive-from": "select_source_spc:match",
                            "block": "th_TH-id_ID-SentencePieceBlockEncode"
                        },
                        "select_source": {
                            "receive-from": {
                                "control": "spm_encode_src",
                                "value": "spm_encode_src"
                            },
                            "block": "th_TH-id_ID-SelectBlock"
                        },
                        "select_target": {
                            "receive-from": {
                                "value": "spm_encode_pb_translation",
                                "control": "spm_encode_src"
                            },
                            "block": "th_TH-id_ID-SelectBlock"
                        },
                        "merge_encoded_source": {
                            "receive-from": {
                                "in2": "spm_encode",
                                "in1": "spm_encode_src"
                            },
                            "block-type": "MergerBlock",
                            "merge-style": "any"
                        },
                        "null_2": {
                            "receive-from": "select_source:match",
                            "block-type": "NullBlock"
                        },
                        "force_align": {
                            "receive-from": {
                                "source": "select_source:pass",
                                "target": "select_target:pass"
                            },
                            "block": "th_TH-id_ID-PDecForceAlignBlock"
                        },
                        "merge_translations_with_needed_alignment_info": {
                            "receive-from": {
                                "in3": "pdec",
                                "in1": "select_target:match",
                                "in2": "force_align"
                            },
                            "block-type": "MergerBlock",
                            "merge-style": "any"
                        },
                        "spm_decode": {
                            "receive-from": "merge_translations_with_needed_alignment_info",
                            "block": "th_TH-id_ID-SentencePieceBlockDecode"
                        },
                        "tokenizer": {
                            "receive-from": "spm_decode",
                            "block": "th_TH-id_ID-AlignmentTokenizerBlock"
                        },
                        "alignment": {
                            "receive-from": {
                                "segmentor-encode": "merge_encoded_source",
                                "pdec-decode": "spm_decode:tokens",
                                "segmentor-decode": "spm_decode",
                                "tokenized": "tokenizer",
                                "source": "graph-input"
                            },
                            "block": "th_TH-id_ID-AlignmentProcessorBlock"
                        },
                        "filter": {
                            "receive-from": "alignment",
                            "block": "th_TH-id_ID-FilterBlock"
                        },
                        "casemap_final": {
                            "receive-from": "filter",
                            "block": "th_TH-id_ID-CaseMapBlock"
                        },
                        "do_not_translate": {
                            "receive-from": {
                                "target": "casemap_final",
                                "source": "graph-input"
                            },
                            "block-type": "DoNotTranslateBlock"
                        },
                        "graph-output": {
                            "receive-from": "do_not_translate"
                        }
                    }
                }
            }
        },
        "mt_app_greedy": {
            "engine-type": "PDEC",
            "block-definitions": {
                "id_ID-th_TH-PhraseBookBlock": {
                    "block-type": "PhraseBookBlock",
                    "enable": true,
                    "nbest": 1,
                    "pb-file-list": "PB-id/PB/id-th.mt_app+mt_app_greedy+siri+system+system_greedy+web.dict",
                    "asset-name": "PB-id"
                },
                "id_ID-th_TH-SentencePieceBlockEncode": {
                    "block-type": "SentencePieceBlock",
                    "action": "encode",
                    "sentence-piece-file": "MT-bi-en-id-th-vi-20/MT/spm.model",
                    "asset-name": "MT-bi-en-id-th-vi-20"
                },
                "id_ID-th_TH-PDecTranslatorBlock": {
                    "block-type": "PDecTranslatorBlock",
                    "model-file": "MT-bi-en-id-th-vi-20/MT/pyespresso.mdl.bin",
                    "model-type": "espresso",
                    "engine-type": "PDEC",
                    "enable-memory-map": true,
                    "confidence-model-file": "",
                    "confidence-threshold": 0,
                    "use-sentencepiece-ids": true,
                    "beam": 1,
                    "lm-mode": "rescore_bpe",
                    "lm-weight": 0.0,
                    "max-seq-length": 200,
                    "max-seq-length-floor": 80,
                    "max-seq-length-relative": 2,
                    "nbest": 1,
                    "norm-costs": true,
                    "reset-meta-info": false,
                    "source-locale": "id_ID",
                    "source-token": "id_ID",
                    "target-locale": "th_TH",
                    "target-token": "th_TH> <id_ID-th_TH-optimal",
                    "unk-replace": true,
                    "veto-factor": 0,
                    "enable_shortlist": true,
                    "merge_shortlist": true,
                    "shortlist-cond-n": 100,
                    "shortlist-freq-n": 100,
                    "shortlist-lang-pair": "all-th",
                    "asset-name": "MT-bi-en-id-th-vi-20"
                },
                "id_ID-th_TH-SelectBlock": {
                    "block-type": "SelectBlock",
                    "match-key": "alignment-queries",
                    "match-wildcard": "**",
                    "match-pattern": [
                        {
                            "start": "**",
                            "end": "**"
                        }
                    ]
                },
                "id_ID-th_TH-PDecForceAlignBlock": {
                    "block-type": "PDecForceAlignBlock",
                    "model-file": "MT-bi-en-id-th-vi-20/MT/pyespresso.mdl.bin",
                    "model-type": "espresso",
                    "nbest": 1,
                    "source-locale": "id_ID",
                    "target-locale": "th_TH",
                    "source-token": "id_ID",
                    "target-token": "th_TH> <id_ID-th_TH-optimal",
                    "use-sentencepiece-ids": true,
                    "enable_shortlist": true,
                    "merge_shortlist": true,
                    "shortlist-cond-n": 100,
                    "shortlist-freq-n": 100,
                    "shortlist-lang-pair": "all-th",
                    "asset-name": "MT-bi-en-id-th-vi-20"
                },
                "id_ID-th_TH-SentencePieceBlockDecode": {
                    "block-type": "SentencePieceBlock",
                    "action": "decode",
                    "sentence-piece-file": "MT-bi-en-id-th-vi-20/MT/spm.model",
                    "asset-name": "MT-bi-en-id-th-vi-20"
                },
                "id_ID-th_TH-AlignmentProcessorBlock": {
                    "block-type": "AlignmentProcessorBlock",
                    "avoid-crossing-words": false,
                    "word-level-alignments": false
                },
                "th_TH-id_ID-PhraseBookBlock": {
                    "block-type": "PhraseBookBlock",
                    "enable": true,
                    "nbest": 1,
                    "pb-file-list": "PB-th/PB/th-id.mt_app+mt_app_greedy+siri+system+system_greedy+web.dict",
                    "asset-name": "PB-th"
                },
                "th_TH-id_ID-SentencePieceBlockEncode": {
                    "block-type": "SentencePieceBlock",
                    "action": "encode",
                    "sentence-piece-file": "MT-bi-en-id-th-vi-20/MT/spm.model",
                    "asset-name": "MT-bi-en-id-th-vi-20"
                },
                "th_TH-id_ID-PDecTranslatorBlock": {
                    "block-type": "PDecTranslatorBlock",
                    "model-file": "MT-bi-en-id-th-vi-20/MT/pyespresso.mdl.bin",
                    "model-type": "espresso",
                    "engine-type": "PDEC",
                    "enable-memory-map": true,
                    "confidence-model-file": "",
                    "confidence-threshold": 0,
                    "use-sentencepiece-ids": true,
                    "beam": 1,
                    "lm-mode": "rescore_bpe",
                    "lm-weight": 0.0,
                    "max-seq-length": 200,
                    "max-seq-length-floor": 80,
                    "max-seq-length-relative": 2,
                    "nbest": 1,
                    "norm-costs": true,
                    "reset-meta-info": false,
                    "source-locale": "th_TH",
                    "source-token": "th_TH",
                    "target-locale": "id_ID",
                    "target-token": "id_ID> <th_TH-id_ID-optimal",
                    "unk-replace": true,
                    "veto-factor": 0,
                    "enable_shortlist": true,
                    "merge_shortlist": true,
                    "shortlist-cond-n": 100,
                    "shortlist-freq-n": 100,
                    "shortlist-lang-pair": "all-id",
                    "asset-name": "MT-bi-en-id-th-vi-20"
                },
                "th_TH-id_ID-SelectBlock": {
                    "block-type": "SelectBlock",
                    "match-key": "alignment-queries",
                    "match-wildcard": "**",
                    "match-pattern": [
                        {
                            "start": "**",
                            "end": "**"
                        }
                    ]
                },
                "th_TH-id_ID-PDecForceAlignBlock": {
                    "block-type": "PDecForceAlignBlock",
                    "model-file": "MT-bi-en-id-th-vi-20/MT/pyespresso.mdl.bin",
                    "model-type": "espresso",
                    "nbest": 1,
                    "source-locale": "th_TH",
                    "target-locale": "id_ID",
                    "source-token": "th_TH",
                    "target-token": "id_ID> <th_TH-id_ID-optimal",
                    "use-sentencepiece-ids": true,
                    "enable_shortlist": true,
                    "merge_shortlist": true,
                    "shortlist-cond-n": 100,
                    "shortlist-freq-n": 100,
                    "shortlist-lang-pair": "all-id",
                    "asset-name": "MT-bi-en-id-th-vi-20"
                },
                "th_TH-id_ID-SentencePieceBlockDecode": {
                    "block-type": "SentencePieceBlock",
                    "action": "decode",
                    "sentence-piece-file": "MT-bi-en-id-th-vi-20/MT/spm.model",
                    "asset-name": "MT-bi-en-id-th-vi-20"
                },
                "th_TH-id_ID-AlignmentTokenizerBlock": {
                    "block-type": "SimpleTokenizerBlock",
                    "tokenizer-file": "MT-bi-en-id-th-vi-20/MT/tokenizer.pat",
                    "asset-name": "MT-bi-en-id-th-vi-20"
                },
                "th_TH-id_ID-AlignmentProcessorBlock": {
                    "block-type": "AlignmentProcessorBlock",
                    "avoid-crossing-words": true,
                    "word-level-alignments": false,
                    "tokenizer": "simple"
                }
            },
            "language-pair-specific-settings": {
                "id_ID-th_TH": {
                    "graph": {
                        "pb": {
                            "receive-from": "graph-input",
                            "block": "id_ID-th_TH-PhraseBookBlock"
                        },
                        "spm_encode": {
                            "receive-from": "pb",
                            "block": "id_ID-th_TH-SentencePieceBlockEncode"
                        },
                        "pdec": {
                            "receive-from": "spm_encode",
                            "block": "id_ID-th_TH-PDecTranslatorBlock"
                        },
                        "spm_encode_pb_translation": {
                            "receive-from": "pb:final",
                            "block": "id_ID-th_TH-SentencePieceBlockEncode"
                        },
                        "merge_encoded_translations": {
                            "receive-from": {
                                "in2": "pdec",
                                "in1": "spm_encode_pb_translation"
                            },
                            "block-type": "MergerBlock",
                            "merge-style": "any"
                        },
                        "select_source_spc": {
                            "receive-from": {
                                "control": "merge_encoded_translations",
                                "value": "graph-input"
                            },
                            "block-type": "SelectBlock",
                            "match-key": "status",
                            "match-pattern": "phrasebook_exact"
                        },
                        "null_1": {
                            "receive-from": "select_source_spc:pass",
                            "block-type": "NullBlock"
                        },
                        "spm_encode_src": {
                            "receive-from": "select_source_spc:match",
                            "block": "id_ID-th_TH-SentencePieceBlockEncode"
                        },
                        "select_source": {
                            "receive-from": {
                                "control": "spm_encode_src",
                                "value": "spm_encode_src"
                            },
                            "block": "id_ID-th_TH-SelectBlock"
                        },
                        "select_target": {
                            "receive-from": {
                                "value": "spm_encode_pb_translation",
                                "control": "spm_encode_src"
                            },
                            "block": "id_ID-th_TH-SelectBlock"
                        },
                        "merge_encoded_source": {
                            "receive-from": {
                                "in2": "spm_encode",
                                "in1": "spm_encode_src"
                            },
                            "block-type": "MergerBlock",
                            "merge-style": "any"
                        },
                        "null_2": {
                            "receive-from": "select_source:match",
                            "block-type": "NullBlock"
                        },
                        "force_align": {
                            "receive-from": {
                                "source": "select_source:pass",
                                "target": "select_target:pass"
                            },
                            "block": "id_ID-th_TH-PDecForceAlignBlock"
                        },
                        "merge_translations_with_needed_alignment_info": {
                            "receive-from": {
                                "in3": "pdec",
                                "in1": "select_target:match",
                                "in2": "force_align"
                            },
                            "block-type": "MergerBlock",
                            "merge-style": "any"
                        },
                        "spm_decode": {
                            "receive-from": "merge_translations_with_needed_alignment_info",
                            "block": "id_ID-th_TH-SentencePieceBlockDecode"
                        },
                        "alignment": {
                            "receive-from": {
                                "segmentor-encode": "merge_encoded_source",
                                "pdec-decode": "spm_decode:tokens",
                                "segmentor-decode": "spm_decode",
                                "source": "graph-input"
                            },
                            "block": "id_ID-th_TH-AlignmentProcessorBlock"
                        },
                        "do_not_translate": {
                            "receive-from": {
                                "target": "alignment",
                                "source": "graph-input"
                            },
                            "block-type": "DoNotTranslateBlock"
                        },
                        "graph-output": {
                            "receive-from": "do_not_translate"
                        }
                    }
                },
                "th_TH-id_ID": {
                    "graph": {
                        "pb": {
                            "receive-from": "graph-input",
                            "block": "th_TH-id_ID-PhraseBookBlock"
                        },
                        "spm_encode": {
                            "receive-from": "pb",
                            "block": "th_TH-id_ID-SentencePieceBlockEncode"
                        },
                        "pdec": {
                            "receive-from": "spm_encode",
                            "block": "th_TH-id_ID-PDecTranslatorBlock"
                        },
                        "spm_encode_pb_translation": {
                            "receive-from": "pb:final",
                            "block": "th_TH-id_ID-SentencePieceBlockEncode"
                        },
                        "merge_encoded_translations": {
                            "receive-from": {
                                "in2": "pdec",
                                "in1": "spm_encode_pb_translation"
                            },
                            "block-type": "MergerBlock",
                            "merge-style": "any"
                        },
                        "select_source_spc": {
                            "receive-from": {
                                "control": "merge_encoded_translations",
                                "value": "graph-input"
                            },
                            "block-type": "SelectBlock",
                            "match-key": "status",
                            "match-pattern": "phrasebook_exact"
                        },
                        "null_1": {
                            "receive-from": "select_source_spc:pass",
                            "block-type": "NullBlock"
                        },
                        "spm_encode_src": {
                            "receive-from": "select_source_spc:match",
                            "block": "th_TH-id_ID-SentencePieceBlockEncode"
                        },
                        "select_source": {
                            "receive-from": {
                                "control": "spm_encode_src",
                                "value": "spm_encode_src"
                            },
                            "block": "th_TH-id_ID-SelectBlock"
                        },
                        "select_target": {
                            "receive-from": {
                                "value": "spm_encode_pb_translation",
                                "control": "spm_encode_src"
                            },
                            "block": "th_TH-id_ID-SelectBlock"
                        },
                        "merge_encoded_source": {
                            "receive-from": {
                                "in2": "spm_encode",
                                "in1": "spm_encode_src"
                            },
                            "block-type": "MergerBlock",
                            "merge-style": "any"
                        },
                        "null_2": {
                            "receive-from": "select_source:match",
                            "block-type": "NullBlock"
                        },
                        "force_align": {
                            "receive-from": {
                                "source": "select_source:pass",
                                "target": "select_target:pass"
                            },
                            "block": "th_TH-id_ID-PDecForceAlignBlock"
                        },
                        "merge_translations_with_needed_alignment_info": {
                            "receive-from": {
                                "in3": "pdec",
                                "in1": "select_target:match",
                                "in2": "force_align"
                            },
                            "block-type": "MergerBlock",
                            "merge-style": "any"
                        },
                        "spm_decode": {
                            "receive-from": "merge_translations_with_needed_alignment_info",
                            "block": "th_TH-id_ID-SentencePieceBlockDecode"
                        },
                        "tokenizer": {
                            "receive-from": "spm_decode",
                            "block": "th_TH-id_ID-AlignmentTokenizerBlock"
                        },
                        "alignment": {
                            "receive-from": {
                                "segmentor-encode": "merge_encoded_source",
                                "pdec-decode": "spm_decode:tokens",
                                "segmentor-decode": "spm_decode",
                                "tokenized": "tokenizer",
                                "source": "graph-input"
                            },
                            "block": "th_TH-id_ID-AlignmentProcessorBlock"
                        },
                        "do_not_translate": {
                            "receive-from": {
                                "target": "alignment",
                                "source": "graph-input"
                            },
                            "block-type": "DoNotTranslateBlock"
                        },
                        "graph-output": {
                            "receive-from": "do_not_translate"
                        }
                    }
                }
            }
        },
        "system": {
            "engine-type": "PDEC",
            "block-definitions": {
                "id_ID-th_TH-PhraseBookBlock": {
                    "block-type": "PhraseBookBlock",
                    "enable": true,
                    "nbest": 4,
                    "pb-file-list": "PB-id/PB/id-th.mt_app+mt_app_greedy+siri+system+system_greedy+web.dict",
                    "asset-name": "PB-id"
                },
                "id_ID-th_TH-SentencePieceBlockEncode": {
                    "block-type": "SentencePieceBlock",
                    "action": "encode",
                    "sentence-piece-file": "MT-bi-en-id-th-vi-20/MT/spm.model",
                    "asset-name": "MT-bi-en-id-th-vi-20"
                },
                "id_ID-th_TH-PDecTranslatorBlock": {
                    "block-type": "PDecTranslatorBlock",
                    "model-file": "MT-bi-en-id-th-vi-20/MT/pyespresso.mdl.bin",
                    "model-type": "espresso",
                    "engine-type": "PDEC",
                    "enable-memory-map": true,
                    "confidence-model-file": "",
                    "confidence-threshold": 0,
                    "use-sentencepiece-ids": true,
                    "beam": 3,
                    "lm-mode": "partial_bias",
                    "lm-weight": 0.25,
                    "max-seq-length": 200,
                    "max-seq-length-floor": 80,
                    "max-seq-length-relative": 2,
                    "norm-costs": true,
                    "partial-input-override": {
                        "beam": 1,
                        "lm-weight": 0.3,
                        "source-token": "partial> <src-id_ID",
                        "veto-factor": 0.0
                    },
                    "reset-meta-info": false,
                    "rs-beam": 0.66,
                    "source-locale": "id_ID",
                    "source-token": "id_ID",
                    "target-locale": "th_TH",
                    "target-token": "th_TH> <id_ID-th_TH-optimal",
                    "unk-replace": true,
                    "veto-factor": 0,
                    "enable_shortlist": true,
                    "merge_shortlist": true,
                    "shortlist-cond-n": 100,
                    "shortlist-freq-n": 100,
                    "shortlist-lang-pair": "all-th",
                    "asset-name": "MT-bi-en-id-th-vi-20"
                },
                "id_ID-th_TH-SelectBlock": {
                    "block-type": "SelectBlock",
                    "match-key": "alignment-queries",
                    "match-wildcard": "**",
                    "match-pattern": [
                        {
                            "start": "**",
                            "end": "**"
                        }
                    ]
                },
                "id_ID-th_TH-PDecForceAlignBlock": {
                    "block-type": "PDecForceAlignBlock",
                    "model-file": "MT-bi-en-id-th-vi-20/MT/pyespresso.mdl.bin",
                    "model-type": "espresso",
                    "nbest": 4,
                    "source-locale": "id_ID",
                    "target-locale": "th_TH",
                    "source-token": "id_ID",
                    "target-token": "th_TH> <id_ID-th_TH-optimal",
                    "use-sentencepiece-ids": true,
                    "enable_shortlist": true,
                    "merge_shortlist": true,
                    "shortlist-cond-n": 100,
                    "shortlist-freq-n": 100,
                    "shortlist-lang-pair": "all-th",
                    "asset-name": "MT-bi-en-id-th-vi-20"
                },
                "id_ID-th_TH-SentencePieceBlockDecode": {
                    "block-type": "SentencePieceBlock",
                    "action": "decode",
                    "sentence-piece-file": "MT-bi-en-id-th-vi-20/MT/spm.model",
                    "asset-name": "MT-bi-en-id-th-vi-20"
                },
                "id_ID-th_TH-AlignmentProcessorBlock": {
                    "block-type": "AlignmentProcessorBlock",
                    "avoid-crossing-words": false,
                    "word-level-alignments": false
                },
                "id_ID-th_TH-FilterBlock": {
                    "locale-validation": true,
                    "source-locale": "id_ID",
                    "block-type": "FilterBlock",
                    "nbest": 1,
                    "enable": true
                },
                "id_ID-th_TH-CaseMapBlock": {
                    "block-type": "CaseMapBlock",
                    "locale": "id"
                },
                "th_TH-id_ID-PhraseBookBlock": {
                    "block-type": "PhraseBookBlock",
                    "enable": true,
                    "nbest": 4,
                    "pb-file-list": "PB-th/PB/th-id.mt_app+mt_app_greedy+siri+system+system_greedy+web.dict",
                    "asset-name": "PB-th"
                },
                "th_TH-id_ID-SentencePieceBlockEncode": {
                    "block-type": "SentencePieceBlock",
                    "action": "encode",
                    "sentence-piece-file": "MT-bi-en-id-th-vi-20/MT/spm.model",
                    "asset-name": "MT-bi-en-id-th-vi-20"
                },
                "th_TH-id_ID-PDecTranslatorBlock": {
                    "block-type": "PDecTranslatorBlock",
                    "model-file": "MT-bi-en-id-th-vi-20/MT/pyespresso.mdl.bin",
                    "model-type": "espresso",
                    "engine-type": "PDEC",
                    "enable-memory-map": true,
                    "confidence-model-file": "",
                    "confidence-threshold": 0,
                    "use-sentencepiece-ids": true,
                    "beam": 3,
                    "lm-mode": "partial_bias",
                    "lm-weight": 0.25,
                    "max-seq-length": 200,
                    "max-seq-length-floor": 80,
                    "max-seq-length-relative": 2,
                    "norm-costs": true,
                    "partial-input-override": {
                        "beam": 1,
                        "lm-weight": 0.3,
                        "source-token": "partial> <src-th_TH",
                        "veto-factor": 0.0
                    },
                    "reset-meta-info": false,
                    "rs-beam": 0.66,
                    "source-locale": "th_TH",
                    "source-token": "th_TH",
                    "target-locale": "id_ID",
                    "target-token": "id_ID> <th_TH-id_ID-optimal",
                    "unk-replace": true,
                    "veto-factor": 0,
                    "enable_shortlist": true,
                    "merge_shortlist": true,
                    "shortlist-cond-n": 100,
                    "shortlist-freq-n": 100,
                    "shortlist-lang-pair": "all-id",
                    "asset-name": "MT-bi-en-id-th-vi-20"
                },
                "th_TH-id_ID-SelectBlock": {
                    "block-type": "SelectBlock",
                    "match-key": "alignment-queries",
                    "match-wildcard": "**",
                    "match-pattern": [
                        {
                            "start": "**",
                            "end": "**"
                        }
                    ]
                },
                "th_TH-id_ID-PDecForceAlignBlock": {
                    "block-type": "PDecForceAlignBlock",
                    "model-file": "MT-bi-en-id-th-vi-20/MT/pyespresso.mdl.bin",
                    "model-type": "espresso",
                    "nbest": 4,
                    "source-locale": "th_TH",
                    "target-locale": "id_ID",
                    "source-token": "th_TH",
                    "target-token": "id_ID> <th_TH-id_ID-optimal",
                    "use-sentencepiece-ids": true,
                    "enable_shortlist": true,
                    "merge_shortlist": true,
                    "shortlist-cond-n": 100,
                    "shortlist-freq-n": 100,
                    "shortlist-lang-pair": "all-id",
                    "asset-name": "MT-bi-en-id-th-vi-20"
                },
                "th_TH-id_ID-SentencePieceBlockDecode": {
                    "block-type": "SentencePieceBlock",
                    "action": "decode",
                    "sentence-piece-file": "MT-bi-en-id-th-vi-20/MT/spm.model",
                    "asset-name": "MT-bi-en-id-th-vi-20"
                },
                "th_TH-id_ID-AlignmentTokenizerBlock": {
                    "block-type": "SimpleTokenizerBlock",
                    "tokenizer-file": "MT-bi-en-id-th-vi-20/MT/tokenizer.pat",
                    "asset-name": "MT-bi-en-id-th-vi-20"
                },
                "th_TH-id_ID-AlignmentProcessorBlock": {
                    "block-type": "AlignmentProcessorBlock",
                    "avoid-crossing-words": true,
                    "word-level-alignments": false,
                    "tokenizer": "simple"
                },
                "th_TH-id_ID-FilterBlock": {
                    "locale-validation": true,
                    "source-locale": "th_TH",
                    "block-type": "FilterBlock",
                    "nbest": 1,
                    "enable": true
                },
                "th_TH-id_ID-CaseMapBlock": {
                    "block-type": "CaseMapBlock",
                    "locale": "th"
                }
            },
            "language-pair-specific-settings": {
                "id_ID-th_TH": {
                    "graph": {
                        "pb": {
                            "receive-from": "graph-input",
                            "block": "id_ID-th_TH-PhraseBookBlock"
                        },
                        "spm_encode": {
                            "receive-from": "pb",
                            "block": "id_ID-th_TH-SentencePieceBlockEncode"
                        },
                        "pdec": {
                            "receive-from": "spm_encode",
                            "block": "id_ID-th_TH-PDecTranslatorBlock"
                        },
                        "spm_encode_pb_translation": {
                            "receive-from": "pb:final",
                            "block": "id_ID-th_TH-SentencePieceBlockEncode"
                        },
                        "merge_encoded_translations": {
                            "receive-from": {
                                "in2": "pdec",
                                "in1": "spm_encode_pb_translation"
                            },
                            "block-type": "MergerBlock",
                            "merge-style": "any"
                        },
                        "select_source_spc": {
                            "receive-from": {
                                "control": "merge_encoded_translations",
                                "value": "graph-input"
                            },
                            "block-type": "SelectBlock",
                            "match-key": "status",
                            "match-pattern": "phrasebook_exact"
                        },
                        "null_1": {
                            "receive-from": "select_source_spc:pass",
                            "block-type": "NullBlock"
                        },
                        "spm_encode_src": {
                            "receive-from": "select_source_spc:match",
                            "block": "id_ID-th_TH-SentencePieceBlockEncode"
                        },
                        "select_source": {
                            "receive-from": {
                                "control": "spm_encode_src",
                                "value": "spm_encode_src"
                            },
                            "block": "id_ID-th_TH-SelectBlock"
                        },
                        "select_target": {
                            "receive-from": {
                                "value": "spm_encode_pb_translation",
                                "control": "spm_encode_src"
                            },
                            "block": "id_ID-th_TH-SelectBlock"
                        },
                        "merge_encoded_source": {
                            "receive-from": {
                                "in2": "spm_encode",
                                "in1": "spm_encode_src"
                            },
                            "block-type": "MergerBlock",
                            "merge-style": "any"
                        },
                        "null_2": {
                            "receive-from": "select_source:match",
                            "block-type": "NullBlock"
                        },
                        "force_align": {
                            "receive-from": {
                                "source": "select_source:pass",
                                "target": "select_target:pass"
                            },
                            "block": "id_ID-th_TH-PDecForceAlignBlock"
                        },
                        "merge_translations_with_needed_alignment_info": {
                            "receive-from": {
                                "in3": "pdec",
                                "in1": "select_target:match",
                                "in2": "force_align"
                            },
                            "block-type": "MergerBlock",
                            "merge-style": "any"
                        },
                        "spm_decode": {
                            "receive-from": "merge_translations_with_needed_alignment_info",
                            "block": "id_ID-th_TH-SentencePieceBlockDecode"
                        },
                        "alignment": {
                            "receive-from": {
                                "segmentor-encode": "merge_encoded_source",
                                "pdec-decode": "spm_decode:tokens",
                                "segmentor-decode": "spm_decode",
                                "source": "graph-input"
                            },
                            "block": "id_ID-th_TH-AlignmentProcessorBlock"
                        },
                        "filter": {
                            "receive-from": "alignment",
                            "block": "id_ID-th_TH-FilterBlock"
                        },
                        "casemap_final": {
                            "receive-from": "filter",
                            "block": "id_ID-th_TH-CaseMapBlock"
                        },
                        "do_not_translate": {
                            "receive-from": {
                                "target": "casemap_final",
                                "source": "graph-input"
                            },
                            "block-type": "DoNotTranslateBlock"
                        },
                        "graph-output": {
                            "receive-from": "do_not_translate"
                        }
                    }
                },
                "th_TH-id_ID": {
                    "graph": {
                        "pb": {
                            "receive-from": "graph-input",
                            "block": "th_TH-id_ID-PhraseBookBlock"
                        },
                        "spm_encode": {
                            "receive-from": "pb",
                            "block": "th_TH-id_ID-SentencePieceBlockEncode"
                        },
                        "pdec": {
                            "receive-from": "spm_encode",
                            "block": "th_TH-id_ID-PDecTranslatorBlock"
                        },
                        "spm_encode_pb_translation": {
                            "receive-from": "pb:final",
                            "block": "th_TH-id_ID-SentencePieceBlockEncode"
                        },
                        "merge_encoded_translations": {
                            "receive-from": {
                                "in2": "pdec",
                                "in1": "spm_encode_pb_translation"
                            },
                            "block-type": "MergerBlock",
                            "merge-style": "any"
                        },
                        "select_source_spc": {
                            "receive-from": {
                                "control": "merge_encoded_translations",
                                "value": "graph-input"
                            },
                            "block-type": "SelectBlock",
                            "match-key": "status",
                            "match-pattern": "phrasebook_exact"
                        },
                        "null_1": {
                            "receive-from": "select_source_spc:pass",
                            "block-type": "NullBlock"
                        },
                        "spm_encode_src": {
                            "receive-from": "select_source_spc:match",
                            "block": "th_TH-id_ID-SentencePieceBlockEncode"
                        },
                        "select_source": {
                            "receive-from": {
                                "control": "spm_encode_src",
                                "value": "spm_encode_src"
                            },
                            "block": "th_TH-id_ID-SelectBlock"
                        },
                        "select_target": {
                            "receive-from": {
                                "value": "spm_encode_pb_translation",
                                "control": "spm_encode_src"
                            },
                            "block": "th_TH-id_ID-SelectBlock"
                        },
                        "merge_encoded_source": {
                            "receive-from": {
                                "in2": "spm_encode",
                                "in1": "spm_encode_src"
                            },
                            "block-type": "MergerBlock",
                            "merge-style": "any"
                        },
                        "null_2": {
                            "receive-from": "select_source:match",
                            "block-type": "NullBlock"
                        },
                        "force_align": {
                            "receive-from": {
                                "source": "select_source:pass",
                                "target": "select_target:pass"
                            },
                            "block": "th_TH-id_ID-PDecForceAlignBlock"
                        },
                        "merge_translations_with_needed_alignment_info": {
                            "receive-from": {
                                "in3": "pdec",
                                "in1": "select_target:match",
                                "in2": "force_align"
                            },
                            "block-type": "MergerBlock",
                            "merge-style": "any"
                        },
                        "spm_decode": {
                            "receive-from": "merge_translations_with_needed_alignment_info",
                            "block": "th_TH-id_ID-SentencePieceBlockDecode"
                        },
                        "tokenizer": {
                            "receive-from": "spm_decode",
                            "block": "th_TH-id_ID-AlignmentTokenizerBlock"
                        },
                        "alignment": {
                            "receive-from": {
                                "segmentor-encode": "merge_encoded_source",
                                "pdec-decode": "spm_decode:tokens",
                                "segmentor-decode": "spm_decode",
                                "tokenized": "tokenizer",
                                "source": "graph-input"
                            },
                            "block": "th_TH-id_ID-AlignmentProcessorBlock"
                        },
                        "filter": {
                            "receive-from": "alignment",
                            "block": "th_TH-id_ID-FilterBlock"
                        },
                        "casemap_final": {
                            "receive-from": "filter",
                            "block": "th_TH-id_ID-CaseMapBlock"
                        },
                        "do_not_translate": {
                            "receive-from": {
                                "target": "casemap_final",
                                "source": "graph-input"
                            },
                            "block-type": "DoNotTranslateBlock"
                        },
                        "graph-output": {
                            "receive-from": "do_not_translate"
                        }
                    }
                }
            }
        },
        "system_greedy": {
            "engine-type": "PDEC",
            "block-definitions": {
                "id_ID-th_TH-PhraseBookBlock": {
                    "block-type": "PhraseBookBlock",
                    "enable": true,
                    "nbest": 1,
                    "pb-file-list": "PB-id/PB/id-th.mt_app+mt_app_greedy+siri+system+system_greedy+web.dict",
                    "asset-name": "PB-id"
                },
                "id_ID-th_TH-SentencePieceBlockEncode": {
                    "block-type": "SentencePieceBlock",
                    "action": "encode",
                    "sentence-piece-file": "MT-bi-en-id-th-vi-20/MT/spm.model",
                    "asset-name": "MT-bi-en-id-th-vi-20"
                },
                "id_ID-th_TH-PDecTranslatorBlock": {
                    "block-type": "PDecTranslatorBlock",
                    "model-file": "MT-bi-en-id-th-vi-20/MT/pyespresso.mdl.bin",
                    "model-type": "espresso",
                    "engine-type": "PDEC",
                    "enable-memory-map": true,
                    "confidence-model-file": "",
                    "confidence-threshold": 0,
                    "use-sentencepiece-ids": true,
                    "beam": 1,
                    "lm-mode": "rescore_bpe",
                    "lm-weight": 0.0,
                    "max-seq-length": 200,
                    "max-seq-length-floor": 80,
                    "max-seq-length-relative": 2,
                    "nbest": 1,
                    "norm-costs": true,
                    "reset-meta-info": false,
                    "source-locale": "id_ID",
                    "source-token": "id_ID",
                    "target-locale": "th_TH",
                    "target-token": "th_TH> <id_ID-th_TH-optimal",
                    "unk-replace": true,
                    "veto-factor": 0,
                    "enable_shortlist": true,
                    "merge_shortlist": true,
                    "shortlist-cond-n": 100,
                    "shortlist-freq-n": 100,
                    "shortlist-lang-pair": "all-th",
                    "asset-name": "MT-bi-en-id-th-vi-20"
                },
                "id_ID-th_TH-SelectBlock": {
                    "block-type": "SelectBlock",
                    "match-key": "alignment-queries",
                    "match-wildcard": "**",
                    "match-pattern": [
                        {
                            "start": "**",
                            "end": "**"
                        }
                    ]
                },
                "id_ID-th_TH-PDecForceAlignBlock": {
                    "block-type": "PDecForceAlignBlock",
                    "model-file": "MT-bi-en-id-th-vi-20/MT/pyespresso.mdl.bin",
                    "model-type": "espresso",
                    "nbest": 1,
                    "source-locale": "id_ID",
                    "target-locale": "th_TH",
                    "source-token": "id_ID",
                    "target-token": "th_TH> <id_ID-th_TH-optimal",
                    "use-sentencepiece-ids": true,
                    "enable_shortlist": true,
                    "merge_shortlist": true,
                    "shortlist-cond-n": 100,
                    "shortlist-freq-n": 100,
                    "shortlist-lang-pair": "all-th",
                    "asset-name": "MT-bi-en-id-th-vi-20"
                },
                "id_ID-th_TH-SentencePieceBlockDecode": {
                    "block-type": "SentencePieceBlock",
                    "action": "decode",
                    "sentence-piece-file": "MT-bi-en-id-th-vi-20/MT/spm.model",
                    "asset-name": "MT-bi-en-id-th-vi-20"
                },
                "id_ID-th_TH-AlignmentProcessorBlock": {
                    "block-type": "AlignmentProcessorBlock",
                    "avoid-crossing-words": false,
                    "word-level-alignments": false
                },
                "th_TH-id_ID-PhraseBookBlock": {
                    "block-type": "PhraseBookBlock",
                    "enable": true,
                    "nbest": 1,
                    "pb-file-list": "PB-th/PB/th-id.mt_app+mt_app_greedy+siri+system+system_greedy+web.dict",
                    "asset-name": "PB-th"
                },
                "th_TH-id_ID-SentencePieceBlockEncode": {
                    "block-type": "SentencePieceBlock",
                    "action": "encode",
                    "sentence-piece-file": "MT-bi-en-id-th-vi-20/MT/spm.model",
                    "asset-name": "MT-bi-en-id-th-vi-20"
                },
                "th_TH-id_ID-PDecTranslatorBlock": {
                    "block-type": "PDecTranslatorBlock",
                    "model-file": "MT-bi-en-id-th-vi-20/MT/pyespresso.mdl.bin",
                    "model-type": "espresso",
                    "engine-type": "PDEC",
                    "enable-memory-map": true,
                    "confidence-model-file": "",
                    "confidence-threshold": 0,
                    "use-sentencepiece-ids": true,
                    "beam": 1,
                    "lm-mode": "rescore_bpe",
                    "lm-weight": 0.0,
                    "max-seq-length": 200,
                    "max-seq-length-floor": 80,
                    "max-seq-length-relative": 2,
                    "nbest": 1,
                    "norm-costs": true,
                    "reset-meta-info": false,
                    "source-locale": "th_TH",
                    "source-token": "th_TH",
                    "target-locale": "id_ID",
                    "target-token": "id_ID> <th_TH-id_ID-optimal",
                    "unk-replace": true,
                    "veto-factor": 0,
                    "enable_shortlist": true,
                    "merge_shortlist": true,
                    "shortlist-cond-n": 100,
                    "shortlist-freq-n": 100,
                    "shortlist-lang-pair": "all-id",
                    "asset-name": "MT-bi-en-id-th-vi-20"
                },
                "th_TH-id_ID-SelectBlock": {
                    "block-type": "SelectBlock",
                    "match-key": "alignment-queries",
                    "match-wildcard": "**",
                    "match-pattern": [
                        {
                            "start": "**",
                            "end": "**"
                        }
                    ]
                },
                "th_TH-id_ID-PDecForceAlignBlock": {
                    "block-type": "PDecForceAlignBlock",
                    "model-file": "MT-bi-en-id-th-vi-20/MT/pyespresso.mdl.bin",
                    "model-type": "espresso",
                    "nbest": 1,
                    "source-locale": "th_TH",
                    "target-locale": "id_ID",
                    "source-token": "th_TH",
                    "target-token": "id_ID> <th_TH-id_ID-optimal",
                    "use-sentencepiece-ids": true,
                    "enable_shortlist": true,
                    "merge_shortlist": true,
                    "shortlist-cond-n": 100,
                    "shortlist-freq-n": 100,
                    "shortlist-lang-pair": "all-id",
                    "asset-name": "MT-bi-en-id-th-vi-20"
                },
                "th_TH-id_ID-SentencePieceBlockDecode": {
                    "block-type": "SentencePieceBlock",
                    "action": "decode",
                    "sentence-piece-file": "MT-bi-en-id-th-vi-20/MT/spm.model",
                    "asset-name": "MT-bi-en-id-th-vi-20"
                },
                "th_TH-id_ID-AlignmentTokenizerBlock": {
                    "block-type": "SimpleTokenizerBlock",
                    "tokenizer-file": "MT-bi-en-id-th-vi-20/MT/tokenizer.pat",
                    "asset-name": "MT-bi-en-id-th-vi-20"
                },
                "th_TH-id_ID-AlignmentProcessorBlock": {
                    "block-type": "AlignmentProcessorBlock",
                    "avoid-crossing-words": true,
                    "word-level-alignments": false,
                    "tokenizer": "simple"
                }
            },
            "language-pair-specific-settings": {
                "id_ID-th_TH": {
                    "graph": {
                        "pb": {
                            "receive-from": "graph-input",
                            "block": "id_ID-th_TH-PhraseBookBlock"
                        },
                        "spm_encode": {
                            "receive-from": "pb",
                            "block": "id_ID-th_TH-SentencePieceBlockEncode"
                        },
                        "pdec": {
                            "receive-from": "spm_encode",
                            "block": "id_ID-th_TH-PDecTranslatorBlock"
                        },
                        "spm_encode_pb_translation": {
                            "receive-from": "pb:final",
                            "block": "id_ID-th_TH-SentencePieceBlockEncode"
                        },
                        "merge_encoded_translations": {
                            "receive-from": {
                                "in2": "pdec",
                                "in1": "spm_encode_pb_translation"
                            },
                            "block-type": "MergerBlock",
                            "merge-style": "any"
                        },
                        "select_source_spc": {
                            "receive-from": {
                                "control": "merge_encoded_translations",
                                "value": "graph-input"
                            },
                            "block-type": "SelectBlock",
                            "match-key": "status",
                            "match-pattern": "phrasebook_exact"
                        },
                        "null_1": {
                            "receive-from": "select_source_spc:pass",
                            "block-type": "NullBlock"
                        },
                        "spm_encode_src": {
                            "receive-from": "select_source_spc:match",
                            "block": "id_ID-th_TH-SentencePieceBlockEncode"
                        },
                        "select_source": {
                            "receive-from": {
                                "control": "spm_encode_src",
                                "value": "spm_encode_src"
                            },
                            "block": "id_ID-th_TH-SelectBlock"
                        },
                        "select_target": {
                            "receive-from": {
                                "value": "spm_encode_pb_translation",
                                "control": "spm_encode_src"
                            },
                            "block": "id_ID-th_TH-SelectBlock"
                        },
                        "merge_encoded_source": {
                            "receive-from": {
                                "in2": "spm_encode",
                                "in1": "spm_encode_src"
                            },
                            "block-type": "MergerBlock",
                            "merge-style": "any"
                        },
                        "null_2": {
                            "receive-from": "select_source:match",
                            "block-type": "NullBlock"
                        },
                        "force_align": {
                            "receive-from": {
                                "source": "select_source:pass",
                                "target": "select_target:pass"
                            },
                            "block": "id_ID-th_TH-PDecForceAlignBlock"
                        },
                        "merge_translations_with_needed_alignment_info": {
                            "receive-from": {
                                "in3": "pdec",
                                "in1": "select_target:match",
                                "in2": "force_align"
                            },
                            "block-type": "MergerBlock",
                            "merge-style": "any"
                        },
                        "spm_decode": {
                            "receive-from": "merge_translations_with_needed_alignment_info",
                            "block": "id_ID-th_TH-SentencePieceBlockDecode"
                        },
                        "alignment": {
                            "receive-from": {
                                "segmentor-encode": "merge_encoded_source",
                                "pdec-decode": "spm_decode:tokens",
                                "segmentor-decode": "spm_decode",
                                "source": "graph-input"
                            },
                            "block": "id_ID-th_TH-AlignmentProcessorBlock"
                        },
                        "do_not_translate": {
                            "receive-from": {
                                "target": "alignment",
                                "source": "graph-input"
                            },
                            "block-type": "DoNotTranslateBlock"
                        },
                        "graph-output": {
                            "receive-from": "do_not_translate"
                        }
                    }
                },
                "th_TH-id_ID": {
                    "graph": {
                        "pb": {
                            "receive-from": "graph-input",
                            "block": "th_TH-id_ID-PhraseBookBlock"
                        },
                        "spm_encode": {
                            "receive-from": "pb",
                            "block": "th_TH-id_ID-SentencePieceBlockEncode"
                        },
                        "pdec": {
                            "receive-from": "spm_encode",
                            "block": "th_TH-id_ID-PDecTranslatorBlock"
                        },
                        "spm_encode_pb_translation": {
                            "receive-from": "pb:final",
                            "block": "th_TH-id_ID-SentencePieceBlockEncode"
                        },
                        "merge_encoded_translations": {
                            "receive-from": {
                                "in2": "pdec",
                                "in1": "spm_encode_pb_translation"
                            },
                            "block-type": "MergerBlock",
                            "merge-style": "any"
                        },
                        "select_source_spc": {
                            "receive-from": {
                                "control": "merge_encoded_translations",
                                "value": "graph-input"
                            },
                            "block-type": "SelectBlock",
                            "match-key": "status",
                            "match-pattern": "phrasebook_exact"
                        },
                        "null_1": {
                            "receive-from": "select_source_spc:pass",
                            "block-type": "NullBlock"
                        },
                        "spm_encode_src": {
                            "receive-from": "select_source_spc:match",
                            "block": "th_TH-id_ID-SentencePieceBlockEncode"
                        },
                        "select_source": {
                            "receive-from": {
                                "control": "spm_encode_src",
                                "value": "spm_encode_src"
                            },
                            "block": "th_TH-id_ID-SelectBlock"
                        },
                        "select_target": {
                            "receive-from": {
                                "value": "spm_encode_pb_translation",
                                "control": "spm_encode_src"
                            },
                            "block": "th_TH-id_ID-SelectBlock"
                        },
                        "merge_encoded_source": {
                            "receive-from": {
                                "in2": "spm_encode",
                                "in1": "spm_encode_src"
                            },
                            "block-type": "MergerBlock",
                            "merge-style": "any"
                        },
                        "null_2": {
                            "receive-from": "select_source:match",
                            "block-type": "NullBlock"
                        },
                        "force_align": {
                            "receive-from": {
                                "source": "select_source:pass",
                                "target": "select_target:pass"
                            },
                            "block": "th_TH-id_ID-PDecForceAlignBlock"
                        },
                        "merge_translations_with_needed_alignment_info": {
                            "receive-from": {
                                "in3": "pdec",
                                "in1": "select_target:match",
                                "in2": "force_align"
                            },
                            "block-type": "MergerBlock",
                            "merge-style": "any"
                        },
                        "spm_decode": {
                            "receive-from": "merge_translations_with_needed_alignment_info",
                            "block": "th_TH-id_ID-SentencePieceBlockDecode"
                        },
                        "tokenizer": {
                            "receive-from": "spm_decode",
                            "block": "th_TH-id_ID-AlignmentTokenizerBlock"
                        },
                        "alignment": {
                            "receive-from": {
                                "segmentor-encode": "merge_encoded_source",
                                "pdec-decode": "spm_decode:tokens",
                                "segmentor-decode": "spm_decode",
                                "tokenized": "tokenizer",
                                "source": "graph-input"
                            },
                            "block": "th_TH-id_ID-AlignmentProcessorBlock"
                        },
                        "do_not_translate": {
                            "receive-from": {
                                "target": "alignment",
                                "source": "graph-input"
                            },
                            "block-type": "DoNotTranslateBlock"
                        },
                        "graph-output": {
                            "receive-from": "do_not_translate"
                        }
                    }
                }
            }
        }
    }
}